AUTHORS
CHANGES.md
LICENSE
MANIFEST.in
README.md
requirements.txt
requirements_test.txt
setup.cfg
setup.py
tox.ini
aio_jsonrpc_2.0.egg-info/PKG-INFO
aio_jsonrpc_2.0.egg-info/SOURCES.txt
aio_jsonrpc_2.0.egg-info/dependency_links.txt
aio_jsonrpc_2.0.egg-info/top_level.txt
aio_jsonrpc_20/__init__.py
aio_jsonrpc_20/builder.py
aio_jsonrpc_20/exception.py
aio_jsonrpc_20/resolver.py
aio_jsonrpc_20/response.py
aio_jsonrpc_20/utils.py
aio_jsonrpc_20/version.py