Metadata-Version: 2.1
Name: aio-jsonrpc-2.0
Version: 0.1.2
Summary: fast JSON-RPC protocol implementation for asyncio, without transport
Home-page: https://github.com/steffgrez/aio-jsonrpc-2.0
Author: Lahache Stephane
Author-email: slahache@gmail.com
License: MIT
Keywords: json rpc jsonrpc json-rpc 2.0
Platform: UNKNOWN
Classifier: Development Status :: 5 - Production/Stable
Classifier: Environment :: Console
Classifier: License :: OSI Approved :: MIT License
Classifier: Natural Language :: English
Classifier: Intended Audience :: Developers
Classifier: Operating System :: OS Independent
Classifier: Programming Language :: Python :: 3.5
Classifier: Programming Language :: Python :: 3.6
Classifier: Topic :: Software Development :: Libraries :: Python Modules
